{
    "links" : [
        { "title" : "（紧急）关于可橙事件", "href" : "https://www.bilibili.com/read/cv8611558", "from" : "bilibili" }, 
        { "title" : "（紧急）关于可橙事件", "href" : "https://zhuanlan.zhihu.com/p/323504466", "from" : "zhihu" }, 
        { "title" : "如何看待山东一成年公民疑似被亲属雇佣「假警察」强制送到戒网瘾机构，进行非法拘禁和强制「医疗」？", "href" : "https://www.zhihu.com/question/432620121", "from" : "zhihu" }, 
        { "title" : "关于 2020 年山东某家长借假警察之手把参加 OI 的成年孩子强行送去戒网瘾学校", "href" : "https://zhuanlan.zhihu.com/p/322400052", "from" : "zhihu" }, 
        { "title" : "关于“可橙事件我个人的看法”（山东一信息竞赛选手被强制送至“戒网瘾学校”一事）", "href" : "https://zhuanlan.zhihu.com/p/322410742", "from" : "zhihu" }, 
        { "title" : "SD省有一个OIer被送到戒网瘾学校了", "href" : "https://www.luogu.com.cn/discuss/show/282170", "from" : "luogu" },
        { "title" : "微博国际版线索（含报警录音）", "href" : "http://weibointl.api.weibo.com/share/186961705.html?weibo_id=4576745069751862", "from" : "weibo"},  
        { "title" : "Problem M - THUPC2021", "href" : "javascript:void(0)", "from" : "THUPC2021" }
    ], 
    "posts" : [
        { "title" : "示例", "href" : "https://github.com/qz-cqy/oier-kecheng/blob/master/post/example.md", "author" : "default" }
    ]
}